prep2dbt/__init__.py
prep2dbt/__main__.py
prep2dbt/__version__.py
prep2dbt/cli.py
prep2dbt/core_services.py
prep2dbt/dbt_services.py
prep2dbt/describe_services.py
prep2dbt/exceptions.py
prep2dbt/options.py
prep2dbt/sqlalchemy_utils.py
prep2dbt/utils.py
prep2dbt/converters/__init__.py
prep2dbt/converters/factory.py
prep2dbt/converters/annotations/__init__.py
prep2dbt/converters/annotations/factory.py
prep2dbt/converters/annotations/add_column/__init__.py
prep2dbt/converters/annotations/add_column/add_column.py
prep2dbt/converters/annotations/change_column_type/__init__.py
prep2dbt/converters/annotations/change_column_type/change_column_type.py
prep2dbt/converters/annotations/duplicate_column/__init__.py
prep2dbt/converters/annotations/duplicate_column/duplicate_column.py
prep2dbt/converters/annotations/filter_operation/__init__.py
prep2dbt/converters/annotations/filter_operation/filter_operation.py
prep2dbt/converters/annotations/keep_only_columns/__init__.py
prep2dbt/converters/annotations/keep_only_columns/keep_only_columns.py
prep2dbt/converters/annotations/mixins/__init__.py
prep2dbt/converters/annotations/mixins/unknown_annotation_mixin.py
prep2dbt/converters/annotations/quick_calc_column/__init__.py
prep2dbt/converters/annotations/quick_calc_column/quick_calc_column.py
prep2dbt/converters/annotations/remap/__init__.py
prep2dbt/converters/annotations/remap/remap.py
prep2dbt/converters/annotations/remove_columns/__init__.py
prep2dbt/converters/annotations/remove_columns/remove_columns.py
prep2dbt/converters/annotations/rename_column/__init__.py
prep2dbt/converters/annotations/rename_column/rename_column.py
prep2dbt/converters/annotations/unknown/__init__.py
prep2dbt/converters/annotations/unknown/unknown.py
prep2dbt/converters/container/__init__.py
prep2dbt/converters/container/converter.py
prep2dbt/converters/load_csv/__init__.py
prep2dbt/converters/load_csv/converter.py
prep2dbt/converters/load_csv_input_union/__init__.py
prep2dbt-0.0.3.dist-info/LICENSE
prep2dbt-0.0.3.dist-info/METADATA
prep2dbt-0.0.3.dist-info/WHEEL
prep2dbt-0.0.3.dist-info/entry_points.txt
prep2dbt-0.0.3.dist-info/top_level.txt
prep2dbt-0.0.3.dist-info/RECORD
