Metadata-Version: 2.1
Name: prep2dbt
Version: 0.0.3
Summary: Tools for converting Tableau Prep flows to dbt models
Author-email: Tomomi Kodama <t.kodama@datumstudio.jp>
License: MIT License
Project-URL: Documentation, https://github.com/t0momi219/prep2dbt
Project-URL: Changelog, https://github.com/t0momi219/prep2dbt
Project-URL: Repository, https://github.com/t0momi219/prep2dbt
Project-URL: Issues, https://github.com/t0momi219/prep2dbt
Keywords: Tableau,dbt
Classifier: Development Status :: 3 - Alpha
Requires-Python: >=3.11
License-File: LICENSE
Requires-Dist: click >=8.1.7
Requires-Dist: networkx >=3.2.1
Requires-Dist: pandas >=2.1.4
Requires-Dist: ruamel.yaml >=0.18.5
Requires-Dist: snowflake-sqlalchemy >=1.5.1
Requires-Dist: sqlalchemy[mypy] >=1.4.50
